langchain_mcp_adapters/__init__.py
langchain_mcp_adapters/client.py
langchain_mcp_adapters/prompts.py
langchain_mcp_adapters/tools.py
orange_langchain_mcp_adapters-0.0.7.dist-info/METADATA
orange_langchain_mcp_adapters-0.0.7.dist-info/WHEEL
orange_langchain_mcp_adapters-0.0.7.dist-info/entry_points.txt
orange_langchain_mcp_adapters-0.0.7.dist-info/licenses/LICENSE
orange_langchain_mcp_adapters-0.0.7.dist-info/RECORD
