Metadata-Version: 2.1
Name: orange-langchain-mcp-adapters
Version: 0.0.7
Summary: Make Anthropic Model Context Protocol (MCP) tools compatible with LangChain and LangGraph agents.
Author-Email: Vadym Barda <19161700+vbarda@users.noreply.github.com>
Requires-Python: >=3.10
Requires-Dist: langchain-core<0.4,>=0.3.36
Requires-Dist: mcp<1.7,>=1.4.1
